pdf_image_extractor_mcp/__init__.py
pdf_image_extractor_mcp/main.py
pdf_image_extractor_mcp-0.1.4.dist-info/METADATA
pdf_image_extractor_mcp-0.1.4.dist-info/WHEEL
pdf_image_extractor_mcp-0.1.4.dist-info/entry_points.txt
pdf_image_extractor_mcp-0.1.4.dist-info/licenses/LICENSE
pdf_image_extractor_mcp-0.1.4.dist-info/RECORD
