Metadata-Version: 2.4
Name: pdf-image-extractor-mcp
Version: 0.1.4
Summary: MCP server for extracting images from PDFs
License-Expression: MIT
License-File: LICENSE
Classifier: Operating System :: OS Independent
Classifier: Programming Language :: Python :: 3
Classifier: Programming Language :: Python :: 3.10
Classifier: Programming Language :: Python :: 3.11
Classifier: Programming Language :: Python :: 3.12
Classifier: Programming Language :: Python :: 3.13
Classifier: Programming Language :: Python :: 3.14
Requires-Python: >=3.10
Requires-Dist: mcp>=1.24.0
Requires-Dist: pymupdf>=1.26.7
